LICENSE
llmchatbot/__init__.py
llmchatbot/app.py
llmchatbot/controller/__init__.py
llmchatbot/controller/chatter.py
llmchatbot/controller/translator.py
llmchatbot/exit_code.py
llmchatbot/model/__init__.py
llmchatbot/model/data.py
llmchatbot/model/finetune/__init__.py
llmchatbot/model/finetune/executor.py
llmchatbot/model/finetune/model_loader.py
llmchatbot/model/finetune/trainer/__init__.py
llmchatbot/model/finetune/trainer/basic.py
llmchatbot/model/finetune/trainer/speech2text.py
llmchatbot/model/finetune/trainer/text2speech.py
llmchatbot/model/processor.py
llmchatbot/model/utils.py
llmchatbot/utils.py
llmchatbot/view/__init__.py
llmchatbot/view/component.py
llmchatbot/view/utils.py
llmchatbot/view/viewer.py
llmchatbot-1.0.4.dist-info/LICENSE
llmchatbot-1.0.4.dist-info/METADATA
llmchatbot-1.0.4.dist-info/WHEEL
llmchatbot-1.0.4.dist-info/RECORD
