Metadata-Version: 2.1
Name: llmchatbot
Version: 1.0.4
Summary: LLM-based Chatbot
Home-page: https://github.com/egpivo/llmchatbot
Author: Joseph Wang
Author-email: egpivo@gmail.com
Requires-Python: >=3.10.12,<4.0.0
Classifier: Programming Language :: Python :: 3
Classifier: Programming Language :: Python :: 3.11
Classifier: Programming Language :: Python :: 3.12
Requires-Dist: bentoml (==1.0.18)
Requires-Dist: datasets (>=2.11.0,<3.0.0)
Requires-Dist: ffmpeg (>=1.4,<2.0)
Requires-Dist: fsspec (>=2023.9.2,<2024.0.0)
Requires-Dist: gradio (==3.27.0)
Requires-Dist: langchain (>=0.0.136,<0.0.137)
Requires-Dist: librosa (>=0.10.0.post2,<0.11.0)
Requires-Dist: llvmlite (>=0.39.1,<0.40.0)
Requires-Dist: openai (>=0.27.4,<0.28.0)
Requires-Dist: orjson (==3.8.10)
Requires-Dist: python-dotenv (>=1.0.0,<2.0.0)
Requires-Dist: sentencepiece (>=0.1.97,<0.2.0)
Requires-Dist: soundfile (>=0.12.1,<0.13.0)
Requires-Dist: torch (>=2.0.0,!=2.0.1,!=2.1.0)
Requires-Dist: torchaudio (>=2.0.1,<3.0.0)
Requires-Dist: torchvision (>=0.15.1,<0.16.0)
Requires-Dist: transformers (>=4.27.4,<5.0.0)
Requires-Dist: wikipedia (>=1.4.0,<2.0.0)
Project-URL: Repository, https://github.com/egpivo/llmchatbot
